{
"meta":{"test_sets":[],"test_metrics":[],"learn_metrics":[{"best_value":"Min","name":"RMSE"}],"launch_mode":"Train","parameters":"","iteration_count":100,"learn_sets":["learn"],"name":"experiment"},
"iterations":[
{"learn":[112516.3933],"iteration":0,"passed_time":0.007836976813,"remaining_time":0.7758607044},
{"learn":[85949.93583],"iteration":1,"passed_time":0.01454512963,"remaining_time":0.712711352},
{"learn":[71619.03301],"iteration":2,"passed_time":0.02036808145,"remaining_time":0.6585679667},
{"learn":[63777.43429],"iteration":3,"passed_time":0.02608757578,"remaining_time":0.6261018188},
{"learn":[59510.83297],"iteration":4,"passed_time":0.03243698157,"remaining_time":0.6163026498},
{"learn":[56226.01303],"iteration":5,"passed_time":0.03873938775,"remaining_time":0.6069170747},
{"learn":[53470.72581],"iteration":6,"passed_time":0.04411646825,"remaining_time":0.5861187925},
{"learn":[51741.93835],"iteration":7,"passed_time":0.05046349906,"remaining_time":0.5803302392},
{"learn":[50355.45778],"iteration":8,"passed_time":0.05596149523,"remaining_time":0.5658328962},
{"learn":[48930.20108],"iteration":9,"passed_time":0.06183661328,"remaining_time":0.5565295195},
{"learn":[47466.439],"iteration":10,"passed_time":0.06819585232,"remaining_time":0.5517664415},
{"learn":[46749.77386],"iteration":11,"passed_time":0.07377668113,"remaining_time":0.541028995},
{"learn":[45666.82962],"iteration":12,"passed_time":0.07922196941,"remaining_time":0.5301777953},
{"learn":[44800.20641],"iteration":13,"passed_time":0.0848541728,"remaining_time":0.5212470615},
{"learn":[43967.06166],"iteration":14,"passed_time":0.09034450236,"remaining_time":0.5119521801},
{"learn":[43189.23172],"iteration":15,"passed_time":0.09624374521,"remaining_time":0.5052796624},
{"learn":[42593.40987],"iteration":16,"passed_time":0.1018143241,"remaining_time":0.4970934648},
{"learn":[41761.99727],"iteration":17,"passed_time":0.1083348952,"remaining_time":0.4935256335},
{"learn":[41198.60849],"iteration":18,"passed_time":0.1289614745,"remaining_time":0.549783128},
{"learn":[40833.69374],"iteration":19,"passed_time":0.1392621809,"remaining_time":0.5570487235},
{"learn":[40423.6055],"iteration":20,"passed_time":0.14823569,"remaining_time":0.5576485479},
{"learn":[39931.99179],"iteration":21,"passed_time":0.1584937301,"remaining_time":0.5619323157},
{"learn":[39551.63367],"iteration":22,"passed_time":0.1682772741,"remaining_time":0.5633630481},
{"learn":[38922.33195],"iteration":23,"passed_time":0.1776721964,"remaining_time":0.5626286218},
{"learn":[38700.34118],"iteration":24,"passed_time":0.1996306813,"remaining_time":0.5988920439},
{"learn":[38390.69106],"iteration":25,"passed_time":0.2115707075,"remaining_time":0.6021627829},
{"learn":[38112.8562],"iteration":26,"passed_time":0.2208439641,"remaining_time":0.5970966437},
{"learn":[37673.26052],"iteration":27,"passed_time":0.2403980523,"remaining_time":0.6181664201},
{"learn":[37299.96012],"iteration":28,"passed_time":0.2609119242,"remaining_time":0.6387843661},
{"learn":[37103.15864],"iteration":29,"passed_time":0.2696415603,"remaining_time":0.6291636406},
{"learn":[36913.28109],"iteration":30,"passed_time":0.2887576521,"remaining_time":0.642718645},
{"learn":[36345.53508],"iteration":31,"passed_time":0.2998245188,"remaining_time":0.6371271025},
{"learn":[35962.00485],"iteration":32,"passed_time":0.3104876806,"remaining_time":0.6303840788},
{"learn":[35804.75194],"iteration":33,"passed_time":0.3486814062,"remaining_time":0.6768521414},
{"learn":[35451.31267],"iteration":34,"passed_time":0.375047063,"remaining_time":0.6965159741},
{"learn":[35280.48911],"iteration":35,"passed_time":0.4045734437,"remaining_time":0.7192416776},
{"learn":[35111.32799],"iteration":36,"passed_time":0.4257047688,"remaining_time":0.7248486604},
{"learn":[34934.30514],"iteration":37,"passed_time":0.4373517974,"remaining_time":0.7135739852},
{"learn":[34764.03911],"iteration":38,"passed_time":0.4576394628,"remaining_time":0.7157950573},
{"learn":[34501.80314],"iteration":39,"passed_time":0.4770150942,"remaining_time":0.7155226413},
{"learn":[34263.0669],"iteration":40,"passed_time":0.4886565812,"remaining_time":0.7031887388},
{"learn":[34098.82276],"iteration":41,"passed_time":0.5085108752,"remaining_time":0.7022293038},
{"learn":[33914.07576],"iteration":42,"passed_time":0.5407343169,"remaining_time":0.7167873503},
{"learn":[33733.41894],"iteration":43,"passed_time":0.5622018476,"remaining_time":0.7155296242},
{"learn":[33568.57322],"iteration":44,"passed_time":0.5821105161,"remaining_time":0.7114684086},
{"learn":[33431.34916],"iteration":45,"passed_time":0.5945312883,"remaining_time":0.6979280341},
{"learn":[33311.63595],"iteration":46,"passed_time":0.6507128234,"remaining_time":0.7337825456},
{"learn":[33193.87452],"iteration":47,"passed_time":0.6591730034,"remaining_time":0.714104087},
{"learn":[33093.98965],"iteration":48,"passed_time":0.6691804206,"remaining_time":0.6964939071},
{"learn":[32995.68938],"iteration":49,"passed_time":0.6787812995,"remaining_time":0.6787812995},
{"learn":[32782.41699],"iteration":50,"passed_time":0.7089583414,"remaining_time":0.6811560535},
{"learn":[32513.72399],"iteration":51,"passed_time":0.7210720328,"remaining_time":0.6656049534},
{"learn":[32365.43702],"iteration":52,"passed_time":0.7699030454,"remaining_time":0.6827442101},
{"learn":[32277.16237],"iteration":53,"passed_time":0.785942621,"remaining_time":0.6695066772},
{"learn":[32189.77936],"iteration":54,"passed_time":0.8227442748,"remaining_time":0.6731544066},
{"learn":[32062.4891],"iteration":55,"passed_time":0.8434484368,"remaining_time":0.662709486},
{"learn":[31974.71982],"iteration":56,"passed_time":0.8497980926,"remaining_time":0.641075754},
{"learn":[31851.80973],"iteration":57,"passed_time":0.8603243388,"remaining_time":0.6229934867},
{"learn":[31709.41151],"iteration":58,"passed_time":0.8976453633,"remaining_time":0.6237874558},
{"learn":[31640.67994],"iteration":59,"passed_time":0.9112753338,"remaining_time":0.6075168892},
{"learn":[31521.91342],"iteration":60,"passed_time":0.9404070094,"remaining_time":0.6012438257},
{"learn":[31419.96266],"iteration":61,"passed_time":0.9500314298,"remaining_time":0.5822773279},
{"learn":[31344.9016],"iteration":62,"passed_time":0.9785873185,"remaining_time":0.5747258854},
{"learn":[31257.13334],"iteration":63,"passed_time":0.9867685841,"remaining_time":0.5550573286},
{"learn":[31141.61962],"iteration":64,"passed_time":1.004719852,"remaining_time":0.5410029973},
{"learn":[31023.70123],"iteration":65,"passed_time":1.015512763,"remaining_time":0.5231429385},
{"learn":[30955.25644],"iteration":66,"passed_time":1.039580647,"remaining_time":0.512032259},
{"learn":[30897.09659],"iteration":67,"passed_time":1.055302059,"remaining_time":0.4966127335},
{"learn":[30807.48595],"iteration":68,"passed_time":1.062294667,"remaining_time":0.4772628216},
{"learn":[30720.03091],"iteration":69,"passed_time":1.071342218,"remaining_time":0.4591466647},
{"learn":[30672.41057],"iteration":70,"passed_time":1.089172195,"remaining_time":0.4448731501},
{"learn":[30576.9627],"iteration":71,"passed_time":1.107439669,"remaining_time":0.4306709823},
{"learn":[30464.76243],"iteration":72,"passed_time":1.138622161,"remaining_time":0.4211342238},
{"learn":[30329.99307],"iteration":73,"passed_time":1.160252065,"remaining_time":0.407656131},
{"learn":[30289.57104],"iteration":74,"passed_time":1.168012834,"remaining_time":0.3893376114},
{"learn":[30237.61835],"iteration":75,"passed_time":1.1943397,"remaining_time":0.3771599052},
{"learn":[30166.59617],"iteration":76,"passed_time":1.232455884,"remaining_time":0.3681361732},
{"learn":[30081.97279],"iteration":77,"passed_time":1.242145346,"remaining_time":0.3503486873},
{"learn":[30033.96921],"iteration":78,"passed_time":1.25918533,"remaining_time":0.3347201509},
{"learn":[29984.26806],"iteration":79,"passed_time":1.285675944,"remaining_time":0.321418986},
{"learn":[29923.29338],"iteration":80,"passed_time":1.293351672,"remaining_time":0.3033787873},
{"learn":[29886.36019],"iteration":81,"passed_time":1.301328356,"remaining_time":0.285657444},
{"learn":[29841.63808],"iteration":82,"passed_time":1.308879543,"remaining_time":0.2680837619},
{"learn":[29783.87241],"iteration":83,"passed_time":1.316513314,"remaining_time":0.2507644407},
{"learn":[29701.72769],"iteration":84,"passed_time":1.32481562,"remaining_time":0.2337909918},
{"learn":[29656.37945],"iteration":85,"passed_time":1.331565772,"remaining_time":0.2167665211},
{"learn":[29607.87305],"iteration":86,"passed_time":1.350138202,"remaining_time":0.2017447888},
{"learn":[29537.52357],"iteration":87,"passed_time":1.358488466,"remaining_time":0.1852484272},
{"learn":[29492.90116],"iteration":88,"passed_time":1.366347735,"remaining_time":0.1688744391},
{"learn":[29429.44289],"iteration":89,"passed_time":1.404963457,"remaining_time":0.1561070507},
{"learn":[29342.92664],"iteration":90,"passed_time":1.413722259,"remaining_time":0.139818685},
{"learn":[29299.70833],"iteration":91,"passed_time":1.421136323,"remaining_time":0.1235770716},
{"learn":[29268.82061],"iteration":92,"passed_time":1.427677435,"remaining_time":0.1074595919},
{"learn":[29213.95311],"iteration":93,"passed_time":1.44499175,"remaining_time":0.09223351599},
{"learn":[29184.36408],"iteration":94,"passed_time":1.480870495,"remaining_time":0.07794055238},
{"learn":[29161.92763],"iteration":95,"passed_time":1.488397808,"remaining_time":0.06201657533},
{"learn":[29103.02615],"iteration":96,"passed_time":1.497090778,"remaining_time":0.04630177663},
{"learn":[29052.76972],"iteration":97,"passed_time":1.504332551,"remaining_time":0.03070066431},
{"learn":[29011.8286],"iteration":98,"passed_time":1.522659316,"remaining_time":0.01538039713},
{"learn":[28942.63127],"iteration":99,"passed_time":1.530356877,"remaining_time":0}
]}